LICENSE
README.md
setup.py
asana_random_one_on_one/__init__.py
asana_random_one_on_one/__main__.py
asana_random_one_on_one/asana_random_one_on_one.py
asana_random_one_on_one/config.py
asana_random_one_on_one/construct_matches.py
asana_random_one_on_one.egg-info/PKG-INFO
asana_random_one_on_one.egg-info/SOURCES.txt
asana_random_one_on_one.egg-info/dependency_links.txt
asana_random_one_on_one.egg-info/requires.txt
asana_random_one_on_one.egg-info/top_level.txt