Metadata-Version: 2.1
Name: asana-random-one-on-one
Version: 0.0.2
Summary: UNKNOWN
Home-page: UNKNOWN
Author: Asana Inc
License: MIT
Platform: UNKNOWN
Requires-Python: >=3.6
